shipzo_plus/__init__.py
shipzo_plus/plus.py
shipzo_plus_hun-0.1.6.dist-info/METADATA
shipzo_plus_hun-0.1.6.dist-info/WHEEL
shipzo_plus_hun-0.1.6.dist-info/entry_points.txt
shipzo_plus_hun-0.1.6.dist-info/top_level.txt
shipzo_plus_hun-0.1.6.dist-info/RECORD
